pyftle-1.0.3.dist-info/RECORD
pyftle-1.0.3.dist-info/WHEEL
pyftle-1.0.3.dist-info/entry_points.txt
pyftle-1.0.3.dist-info/METADATA
pyftle-1.0.3.dist-info/licenses/LICENSE
pyftle/data_source.py
pyftle/ftle.py
pyftle/cauchy_green.py
pyftle/ftle_solver.py
pyftle/file_readers.py
pyftle/ginterp.cpython-313-darwin.so
pyftle/hyperparameters.py
pyftle/my_types.py
pyftle/__init__.py
pyftle/integrate.py
pyftle/file_writers.py
pyftle/particles.py
pyftle/api.py
pyftle/ginterp.pyi
pyftle/file_utils.py
pyftle/interpolate.py
pyftle/parallel.py
pyftle/__main__.py
pyftle/decorators.py
pyftle/grid_interp/__init__.py
pyftle/grid_interp/GridInterp.cpp
pyftle/grid_interp/grid_interp.py
