Metadata-Version: 2.1
Name: pyFTLE
Version: 1.0.3
Summary: Python package to compute Finite Time Lyapunov Exponents (FTLE).
Requires-Python: >=3.10
Requires-Dist: colorama>=0.4.6
Requires-Dist: configargparse>=1.7
Requires-Dist: matplotlib>=3.10.0
Requires-Dist: nptyping>=2.5.0
Requires-Dist: numba>=0.61.0
Requires-Dist: numpy>=1.26.4
Requires-Dist: pandas>=2.2.3
Requires-Dist: pyevtk>=1.6.0
Requires-Dist: pyvista>=0.46.3
Requires-Dist: scipy>=1.15.1
Requires-Dist: tqdm>=4.67.1
Provides-Extra: dev
Requires-Dist: ruff>=0.9.9; extra == "dev"
Requires-Dist: pyright>=1.1.395; extra == "dev"
Requires-Dist: typos>=1.29.10; extra == "dev"
Requires-Dist: pybind11; extra == "dev"
Requires-Dist: cmake; extra == "dev"
Requires-Dist: ninja; extra == "dev"
Requires-Dist: pybind11-stubgen>=2.5.5; extra == "dev"
Requires-Dist: scipy-stubs>=1.15.2.0; extra == "dev"
Requires-Dist: pandas-stubs>=2.2.3.241126; extra == "dev"
Requires-Dist: types-tqdm>=4.67.0.20241221; extra == "dev"
Requires-Dist: jupyter>=1.1.1; extra == "dev"
Provides-Extra: docs
Requires-Dist: furo>=2025.9.25; extra == "docs"
Requires-Dist: myst-parser>=4.0.1; extra == "docs"
Requires-Dist: sphinx>=8.1.3; extra == "docs"
Requires-Dist: sphinx-autodoc-typehints>=3.0.1; extra == "docs"
Provides-Extra: test
Requires-Dist: pytest>=8.3.4; extra == "test"
Requires-Dist: pytest-mock>=3.14.0; extra == "test"
Requires-Dist: pytest-cov>=6.0.0; extra == "test"
